mkdocs_build_plantuml_plugin_ardihikaru/__init__.py
mkdocs_build_plantuml_plugin_ardihikaru/plantuml.py
mkdocs_build_plantuml_plugin_ardihikaru-1.9.6.dist-info/LICENSE
mkdocs_build_plantuml_plugin_ardihikaru-1.9.6.dist-info/METADATA
mkdocs_build_plantuml_plugin_ardihikaru-1.9.6.dist-info/WHEEL
mkdocs_build_plantuml_plugin_ardihikaru-1.9.6.dist-info/entry_points.txt
mkdocs_build_plantuml_plugin_ardihikaru-1.9.6.dist-info/top_level.txt
mkdocs_build_plantuml_plugin_ardihikaru-1.9.6.dist-info/RECORD
