Metadata-Version: 2.1
Name: mkdocs-build-plantuml-plugin-ardihikaru
Version: 1.9.6
Summary: An MkDocs plugin to call plantuml locally or remote (cloned from: https://github.com/christo-ph/mkdocs_build_plantuml)
Home-page: https://pypi.org/project/mkdocs-build-plantuml-plugin-ardihikaru/1.9.6/#files
Author: Christoph Galler
Author-email: galler@quantor.consulting
License: MIT
Keywords: mkdocs plantuml publishing documentation uml sequence diagram
Classifier: Development Status :: 5 - Production/Stable
Classifier: Intended Audience :: Developers
Classifier: Intended Audience :: Information Technology
Classifier: License :: OSI Approved :: MIT License
Classifier: Programming Language :: Python
Classifier: Programming Language :: Python :: 3 :: Only
Requires-Python: >=3.2
License-File: LICENSE
Requires-Dist: mkdocs >=1.0.4
Requires-Dist: httplib2
